orpy/__init__.py
orpy/exceptions.py
orpy/oidc.py
orpy/shell.py
orpy/utils.py
orpy/version.py
orpy/_cmd/__init__.py
orpy/_cmd/config.py
orpy/_cmd/deployments.py
orpy/_cmd/info.py
orpy/_cmd/resources.py
orpy/client/__init__.py
orpy/client/base.py
orpy/client/client.py
orpy/client/config.py
orpy/client/deployments.py
orpy/client/info.py
orpy/client/resources.py
orpy/tests/__init__.py
orpy/tests/base.py
orpy/tests/test_orpy.py
orpy-1.0.4.dist-info/LICENSE
orpy-1.0.4.dist-info/METADATA
orpy-1.0.4.dist-info/WHEEL
orpy-1.0.4.dist-info/entry_points.txt
orpy-1.0.4.dist-info/pbr.json
orpy-1.0.4.dist-info/top_level.txt
orpy-1.0.4.dist-info/RECORD
