Metadata-Version: 2.1
Name: orpy
Version: 1.0.4
Summary: Python library and CLI for the INDIGO PaaS Orchestrator.
Home-page: https://github.com/indigo-dc/orpy
Author: Alvaro Lopez Garcia
Author-email: aloga@ifca.unican.es
License: Apache-2
Project-URL: Bug Tracker, https://github.com/indigo-dc/orpy/issues
Project-URL: Documentation, https://orpy.readthedocs.io/
Classifier: Development Status :: 5 - Production/Stable
Classifier: Environment :: Console
Classifier: Environment :: Web Environment
Classifier: Intended Audience :: Developers
Classifier: Intended Audience :: Information Technology
Classifier: Intended Audience :: Science/Research
Classifier: Intended Audience :: System Administrators
Classifier: License :: OSI Approved :: Apache Software License
Classifier: Operating System :: OS Independent
Classifier: Programming Language :: Python
Classifier: Programming Language :: Python :: 3
Classifier: Programming Language :: Python :: 3.6
Classifier: Programming Language :: Python :: 3.7
Classifier: Programming Language :: Python :: 3.8
Classifier: Topic :: Internet :: WWW/HTTP
Requires-Python: >=3.6
License-File: LICENSE
Requires-Dist: pbr (>=4.1.0)
Requires-Dist: six (>=1.10.0)
Requires-Dist: pyperclip (!=1.8.1)
Requires-Dist: cliff (!=2.9.0,>=2.8.0)
Requires-Dist: requests
